<?xml version="1.0" encoding="UTF-8"?>
<ptis xmlns:xsi="http://www.w3.org/2001/XMLSchema-instance"
      xsi:noNamespaceSchemaLocation="http://localhost:8080/api/v1/schemas/PTIS/v1.0"
      version="1.0">
  <issuer>REPA</issuer>
  <entity>REPA_EJ_001</entity>
  <period>2026-03</period>
  <lastMonthlyFlow>false</lastMonthlyFlow>
  <payment><invoiceId>REP-01-B2BD-0008-04</invoiceId><amount>251.00</amount><type>PAIEMENT</type></payment>
  <payment><invoiceId>REP-01-B2BD-0009-01</invoiceId><amount>225.00</amount><type>PAIEMENT</type></payment>
</ptis>